<config>
	<runmode>development</runmode>
	<!--（必须） 指定应用的根package，所有内部自动注入都依赖于此package名称，请设置准确。 -->
	<package>cn.icinfo.zuaa</package>
	<web>
		<!--（可选，缺省为root目录下的upload目录，大小为4M) 设置上传文件存放的路径和上传文件的最大尺寸 -->
		<upload>
			<directory></directory>
			<max-size>2096</max-size>
		</upload>
		<!-- (可选)设置Request的编码类型。 -->
		<charset>utf-8</charset>
		<short-dateformat>yyyy.MM.dd</short-dateformat>
		<long-dateformat>yyyy.MM.dd hh:mm:ss</long-dateformat>
		<!--
			(可选，缺省使用cn.quickj.session.MemHttpSession,你还可以选择MemCacheHttpSession进行分布式Session存储，缺省超时30分钟)
			HttpSession的设置。
		-->
	</web>
	<plugins>
		<plugin>
			<class>cn.quickj.jobs.JobsPlugin</class>
			<param>{min:5,max:100,maxWait:5000,host:"127.0.0.1",port:6379,master:true}</param>
		</plugin>
		
	</plugins>
	<!-- 数据库设置 -->
	<database>

	</database>
</config>
